{
    "scripts": [
      {
        "name": "Obi Switcher",
        "author": "Wither123go",
        "desc": "No description provided",
        "contents": "scripts/obi-switcher.ccs"
      },
      {
        "name": "Middle Click Pearl",
        "author": "ImproperIssues",
        "desc": "Middle click your mouse to throw a pearl",
        "contents": "scripts/middle-click-pearl.ccs"
      },
      {
        "name": "Double Click",
        "author": "ImproperIssues",
        "desc": "Clicks a second time when you release your mouse",
        "contents": "scripts/double-clicker.ccs"
      },
      {
        "name": "Auto Totem",
        "author": "ImproperIssues",
        "desc": "Automatically replenishes your totems in your inventory",
        "contents": "scripts/auto-totem.ccs"
      },
      {
        "name": "Anti Weakness",
        "author": "ImproperIssues",
        "desc": "Allows crystalling even if you have weakness",
        "contents": "scripts/no-weak.ccs"
      },
      {
        "name": "Anchor Place",
        "author": "ImproperIssues",
        "desc": "Places a fully charged anchor when you right click your sword",
        "contents": "scripts/op-anchors.ccs"
      },
      {
        "name": "Sworld Hit",
        "author": "ImproperIssues",
        "desc": "Guarantees you hit your opponents with a sword and not anything else",
        "contents": "scripts/sword-hit.ccs"
      },
      {
        "name": "Fast EXP",
        "author": "vgs",
        "desc": "Uses experience bottles quickly while holding right-click",
        "contents": "scripts/fast-exp.ccs"
      },
      {
        "name": "vgs' ez totem",
        "author": "vgs",
        "desc": "totem fast",
        "contents": "scripts/vgs-totem.ccs"
      },
      {
        "name": "All Items KB",
        "author": "Wither123go",
        "desc": "KB for CPvP",
        "contents": "scripts/all-items-kb.ccs"
      },
      {
        "name": "2 Anchor Key",
        "author": "Wither123go",
        "desc": "Press N and double anchor with the speed of light",
        "contents": "scripts/2-anchor-key.ccs"
      },
      {
        "name": "CW CRYSTALS LEGIT",
        "author": "Wither123go",
        "desc": "CW CRYSTALS LEGIT LOOKING",
        "contents": "scripts/cw-crystals-legit.ccs"
      },
      {
        "name": "Safe Anchor Y",
        "author": "Wither123go",
        "desc": "Press Y for safe anchor",
        "contents": "scripts/safe-anchor-y.ccs"
      }
    ]
  }